quercle_langchain/__init__.py
quercle_langchain/py.typed
quercle_langchain/tools.py
langchain_quercle-0.1.4.dist-info/METADATA
langchain_quercle-0.1.4.dist-info/WHEEL
langchain_quercle-0.1.4.dist-info/licenses/LICENSE
langchain_quercle-0.1.4.dist-info/RECORD
