Metadata-Version: 2.4
Name: langchain-quercle
Version: 0.1.4
Summary: LangChain tools for Quercle web search and URL fetching
Project-URL: Homepage, https://github.com/quercledev/quercle-langchain
Project-URL: Documentation, https://quercle.dev/docs
Project-URL: Repository, https://github.com/quercledev/quercle-langchain
Author-email: Quercle <support@quercle.dev>
License-Expression: MIT
License-File: LICENSE
Keywords: ai,langchain,llm,quercle,tools,web-search
Classifier: Development Status :: 4 - Beta
Classifier: Intended Audience :: Developers
Classifier: License :: OSI Approved :: MIT License
Classifier: Programming Language :: Python :: 3
Classifier: Programming Language :: Python :: 3.10
Classifier: Programming Language :: Python :: 3.11
Classifier: Programming Language :: Python :: 3.12
Classifier: Programming Language :: Python :: 3.13
Classifier: Topic :: Scientific/Engineering :: Artificial Intelligence
Requires-Python: >=3.10
Requires-Dist: langchain-core>=0.2.0
Requires-Dist: pydantic>=2.0
Requires-Dist: quercle>=0.1.3
Provides-Extra: dev
Requires-Dist: pytest-asyncio>=0.24; extra == 'dev'
Requires-Dist: pytest>=8.0; extra == 'dev'
Requires-Dist: ruff>=0.8; extra == 'dev'
